{
  "id": "slushie-spout-partially-blocked",
  "lesson": "A slow pour with no alarms and healthy internals points to a plug of crystallised syrup in the spout. Check and clear it before reaching for pumps or parts.",
  "machineType": "slushie-machine",
  "tier": 1,
  "symptoms": [
    "Product pours very slowly.",
    "No alarms.",
    "Staff say it's been slow for weeks."
  ],
  "tests": {
    "error-log": "No faults recorded.",
    "temp-probe": "All temps in spec.",
    "inspect-beater": "Agitator and bowl fine. Dispense spout has a thick plug of crystallised syrup at the tip."
  },
  "correctFix": "clear-and-sanitise-spout",
  "wrongFixes": ["replace-mix-pump", "replace-slushie-thermostat", "replace-bowl-gasket"],
  "payout": 80,
  "partsCost": 0,
  "flavour": "Three minutes with a pipe brush. Invoice is in the post.",
  "authenticityNote": "Dried syrup crystallises inside the spout bore and slowly chokes flow to a trickle. Pure maintenance skip — never a parts job, always preventable."
}
