{
  "id": "slushie-mix-too-weak",
  "lesson": "A frozen block at a normal bowl temperature means the mix is under syrup ratio, not a refrigeration fault — sugar is the antifreeze. Drain and re-mix it.",
  "machineType": "slushie-machine",
  "tier": 1,
  "symptoms": [
    "Left bowl frozen into one solid block.",
    "Auger groaning and barely turning."
  ],
  "tests": {
    "error-log": "AUGER OVERTORQUE trips, repeating since this morning.",
    "temp-probe": "Bowl temp right on setpoint. The refrigeration is doing exactly what it's told.",
    "inspect-beater": "Bowl frozen into one solid mass around the auger. The auger itself is intact — stalling against the ice, not broken."
  },
  "symptomVariants": [
    {
      "symptoms": [
        "Right bowl seized into a glacier overnight.",
        "Drive motor breaker has tripped twice this morning."
      ]
    },
    {
      "symptoms": [
        "Bowl frozen solid the day after the new hire's first solo refill.",
        "Auger stalling with a groan you can hear from the counter."
      ]
    }
  ],
  "correctFix": "drain-and-remix-product",
  "wrongFixes": ["replace-auger-motor", "replace-thermostat", "regas-refrigeration"],
  "payout": 85,
  "partsCost": 0,
  "flavour": "Diagnosis: somebody was stretching the syrup.",
  "authenticityNote": "Sugar is the antifreeze in a slushie — mix that's under the syrup ratio freezes into a solid block instead of staying slush. A genuinely common operator error, usually someone economising on concentrate."
}
